image_service_foundation/__init__.py
image_service_foundation/config/__init__.py
image_service_foundation/config/configuration_manager.py
image_service_foundation/config/utils.py
image_service_foundation/logger.py
image_service_foundation/storage/__init__.py
image_service_foundation/storage/dropbox_cloud.py
image_service_foundation/storage/google_cloud.py
image_service_foundation/storage/models_provider.py
image_service_foundation/version.py
image_service_foundation-0.4.1.dist-info/LICENSE.txt
image_service_foundation-0.4.1.dist-info/METADATA
image_service_foundation-0.4.1.dist-info/WHEEL
image_service_foundation-0.4.1.dist-info/RECORD
