Metadata-Version: 2.1
Name: image-service-foundation
Version: 0.4.1
Summary: 
License: MIT
Author: Anustup Das
Author-email: anustup@mediadistillery.com
Requires-Python: >=3.7,<4.0
Classifier: License :: OSI Approved :: MIT License
Classifier: Programming Language :: Python :: 3
Classifier: Programming Language :: Python :: 3.7
Classifier: Programming Language :: Python :: 3.8
Classifier: Programming Language :: Python :: 3.9
Classifier: Programming Language :: Python :: 3.10
Classifier: Programming Language :: Python :: 3.11
Requires-Dist: PyYAML (>=5.1b3)
Requires-Dist: dropbox (==11.35.0)
Requires-Dist: google-cloud-storage (>=1.35,<2)
Requires-Dist: requests (>=2.21,<3.0)
